ROCIS/downloader/__init__.py
ROCIS/downloader/__main__.py
rocis_downloader-0.1.1.dist-info/METADATA
rocis_downloader-0.1.1.dist-info/WHEEL
rocis_downloader-0.1.1.dist-info/RECORD
